<_>
   <form_key>cMhDxOhYjxaSIDIX</form_key>
   <name>RicoNeitzel_VertNav</name>
   <channel>community</channel>
   <version_ids>
      <version_ids>2</version_ids>
      <version_ids>1</version_ids>
   </version_ids>
   <summary>Vertical Navigation - drop in replacement for the horizontal  top navigation.</summary>
   <description>Lots of css selectors available.</description>
   <license>OSL v3.0</license>
   <license_uri>http://opensource.org/licenses/osl-3.0.php</license_uri>
   <version>0.4.1</version>
   <stability>stable</stability>
   <notes>Add a vertical menu to your site. Features many css classes and several configuration options.</notes>
   <authors>
      <name>
         <name>Vinai Kopp</name>
         <name>Rico Neitzel</name>
      </name>
      <user>
         <user>vinai</user>
         <user>rizi</user>
      </user>
      <email>
         <email>vinai@netzarbeiter.com</email>
         <email>rico@buro71a.de</email>
      </email>
   </authors>
   <depends_php_min>5.2.6</depends_php_min>
   <depends_php_max>6.0.0</depends_php_max>
   <depends>
      <package>
         <name>
            <name/>
         </name>
         <channel>
            <channel/>
         </channel>
         <min>
            <min/>
         </min>
         <max>
            <max/>
         </max>
         <files>
            <files>           </files>
         </files>
      </package>
      <extension>
         <name>
            <name>Core</name>
         </name>
         <min>
            <min/>
         </min>
         <max>
            <max/>
         </max>
      </extension>
   </depends>
   <contents>
      <target>
         <target>magelocal</target>
         <target>magecommunity</target>
         <target>mageetc</target>
         <target>magelocale</target>
         <target>magelocale</target>
         <target>magedesign</target>
         <target>magedesign</target>
         <target>mageskin</target>
         <target>magedesign</target>
         <target>magedesign</target>
         <target>mageskin</target>
      </target>
      <path>
         <path/>
         <path>RicoNeitzel/VertNav</path>
         <path>modules/RicoNeitzel_VertNav.xml</path>
         <path>de_DE/RicoNeitzel_VertNav.csv</path>
         <path>es_MX/RicoNeitzel_VertNav.csv</path>
         <path>frontend/base/default/layout/vertnav.xml</path>
         <path>frontend/base/default/template/vertnav/left.phtml</path>
         <path>frontend/base/default/css/vertnav.css</path>
         <path>frontend/default/default/layout/vertnav.xml</path>
         <path>frontend/default/default/template/vertnav/left.phtml</path>
         <path>frontend/default/default/css/vertnav.css</path>
      </path>
      <type>
         <type>file</type>
         <type>dir</type>
         <type>file</type>
         <type>file</type>
         <type>file</type>
         <type>file</type>
         <type>file</type>
         <type>file</type>
         <type>file</type>
         <type>file</type>
         <type>file</type>
      </type>
      <include>
         <include/>
         <include/>
         <include/>
         <include/>
         <include/>
         <include/>
         <include/>
         <include/>
         <include/>
         <include/>
         <include/>
      </include>
      <ignore>
         <ignore/>
         <ignore/>
         <ignore/>
         <ignore/>
         <ignore/>
         <ignore/>
         <ignore/>
         <ignore/>
         <ignore/>
         <ignore/>
         <ignore/>
      </ignore>
   </contents>
</_>
